<?xml version="1.0" encoding="UTF-8"?>
<mappings xmlns="http://dozer.sourceforge.net"
          xmlns:xsi="http://www.w3.org/2001/XMLSchema-instance"
          xsi:schemaLocation="http://dozer.sourceforge.net
          http://dozer.sourceforge.net/schema/beanmapping.xsd">
    <mapping>
        <class-a>com.dyzzw.blog.vo.PostVo</class-a>
        <class-b>com.dyzzw.blog.search.model.PostDocment</class-b>
        <field>
            <a>id</a>
            <b>id</b>
        </field>
        <field>
            <a>title</a>
            <b>title</b>
        </field>
        <field>
            <a>authodID</a>
            <b>authodID</b>
        </field>
        <field>
            <a>authodName</a>
            <b>authodName</b>
        </field>
        <field>
            <a>authodAvatar</a>
            <b>authodAvatar</b>
        </field>
        <field>
            <a>categoryId</a>
            <b>categoryId</b>
        </field>
        <field>
            <a>CategoryName</a>
            <b>categoryName</b>
        </field>
        <field>
            <a>level</a>
            <b>level</b>
        </field>

        <field>
            <a>recommend</a>
            <b>recommend</b>
        </field>
        <field>
            <a>commentCount</a>
            <b>commentCount</b>
        </field>
        <field>
            <a>viewCount</a>
            <b>viewCount</b>
        </field>
        <field>
            <a date-format="yyyy-MM-dd">created</a>
            <b>created</b>
        </field>
    </mapping>
</mappings>
